cvrmap/__init__.py
cvrmap/cvrmap.py
cvrmap/data/__init__.py
cvrmap/data/reports_config.yml
cvrmap/utils/__init__.py
cvrmap/utils/io_tools.py
cvrmap/utils/math_tools.py
cvrmap/utils/preprocessing.py
cvrmap/utils/processing.py
cvrmap/utils/report.py
cvrmap/utils/shell_tools.py
cvrmap/utils/viz.py
cvrmap/utils/tests/__init__.py
cvrmap/utils/tests/test_io_tools.py
cvrmap/utils/tests/test_math_tools.py
cvrmap/utils/tests/test_shell_tools.py
cvrmap-2.0.20.dist-info/LICENSE
cvrmap-2.0.20.dist-info/METADATA
cvrmap-2.0.20.dist-info/WHEEL
cvrmap-2.0.20.dist-info/entry_points.txt
cvrmap-2.0.20.dist-info/top_level.txt
cvrmap-2.0.20.dist-info/RECORD
