Metadata-Version: 2.1
Name: cvrmap
Version: 2.0.20
Summary: CVRmap is an opensource software to compute maps of Cerebro-Vascular Reactivity
Home-page: https://github.com/ln2t/cvrmap
Author: Antonin Rovai
Author-email: antonin.rovai@hubruxelles.be
License-File: LICENSE
Requires-Dist: astor (==0.8.1)
Requires-Dist: bids-validator (==1.11.0)
Requires-Dist: certifi (==2023.5.7)
Requires-Dist: charset-normalizer (==3.1.0)
Requires-Dist: click (==8.1.3)
Requires-Dist: contourpy (==1.0.7)
Requires-Dist: cycler (==0.11.0)
Requires-Dist: docopt (==0.6.2)
Requires-Dist: fonttools (==4.39.4)
Requires-Dist: formulaic (==0.5.2)
Requires-Dist: greenlet (==2.0.2)
Requires-Dist: idna (==3.4)
Requires-Dist: interface-meta (==1.3.0)
Requires-Dist: joblib (==1.2.0)
Requires-Dist: kaleido (==0.2.1)
Requires-Dist: kiwisolver (==1.4.4)
Requires-Dist: lxml (==4.9.2)
Requires-Dist: matplotlib (==3.7.1)
Requires-Dist: nibabel (==5.1.0)
Requires-Dist: nilearn (==0.10.1)
Requires-Dist: nireports (==23.1.0)
Requires-Dist: jinja2 (==3.1.2)
Requires-Dist: num2words (==0.5.12)
Requires-Dist: numpy (==1.24.3)
Requires-Dist: packaging (==23.1)
Requires-Dist: pandas (==2.0.1)
Requires-Dist: patsy (==0.5.3)
Requires-Dist: PeakUtils (==1.3.4)
Requires-Dist: Pillow (==10.0.0)
Requires-Dist: plotly (==5.14.1)
Requires-Dist: pybids (==0.16.3)
Requires-Dist: pyparsing (==3.0.9)
Requires-Dist: python-dateutil (==2.8.2)
Requires-Dist: pytz (==2023.3)
Requires-Dist: requests (==2.30.0)
Requires-Dist: scikit-learn (==1.2.2)
Requires-Dist: scipy (==1.10.1)
Requires-Dist: six (==1.16.0)
Requires-Dist: SQLAlchemy (==2.0.14)
Requires-Dist: statsmodels (==0.14.0)
Requires-Dist: tenacity (==8.2.2)
Requires-Dist: threadpoolctl (==3.1.0)
Requires-Dist: typing-extensions (==4.5.0)
Requires-Dist: tzdata (==2023.3)
Requires-Dist: xmlformatter (==0.2.4)
Requires-Dist: urllib3 (==2.1.0)
Requires-Dist: uuid (==1.30)
Requires-Dist: wrapt (==1.15.0)
Requires-Dist: pytest (==7.4.3)
Requires-Dist: pytest-cov (==4.1.0)
